{
  "address": "mHzHVz7h2YeiYNgaByaFn977em2sFFEt2vvdxp8khat",
  "metadata": {
    "name": "bakedbeans_solana",
    "version": "0.1.0",
    "spec": "0.1.0",
    "description": "Created with Anchor"
  },
  "instructions": [
    {
      "name": "buy_eggs",
      "docs": [
        "Buy chickens with SOL (amount transferred via preInstruction)"
      ],
      "discriminator": [
        194,
        119,
        28,
        40,
        255,
        8,
        228,
        178
      ],
      "accounts": [
        {
          "name": "global_state",
          "writable": true,
          "pda": {
            "seeds": [
              {
                "kind": "const",
                "value": [
                  103,
                  108,
                  111,
                  98,
                  97,
                  108,
                  95,
                  115,
                  116,
                  97,
                  116,
                  101
                ]
              }
            ]
          }
        },
        {
          "name": "user_state",
          "writable": true,
          "pda": {
            "seeds": [
              {
                "kind": "const",
                "value": [
                  117,
                  115,
                  101,
                  114,
                  95,
                  115,
                  116,
                  97,
                  116,
                  101
                ]
              },
              {
                "kind": "account",
                "path": "buyer"
              }
            ]
          }
        },
        {
          "name": "buyer",
          "writable": true,
          "signer": true
        },
        {
          "name": "vault",
          "writable": true,
          "pda": {
            "seeds": [
              {
                "kind": "const",
                "value": [
                  118,
                  97,
                  117,
                  108,
                  116
                ]
              }
            ]
          }
        },
        {
          "name": "dev_wallet",
          "writable": true
        },
        {
          "name": "referrer_state",
          "writable": true,
          "optional": true
        },
        {
          "name": "system_program",
          "address": "11111111111111111111111111111111"
        }
      ],
      "args": [
        {
          "name": "amount",
          "type": "u64"
        },
        {
          "name": "referrer",
          "type": {
            "option": "pubkey"
          }
        }
      ]
    },
    {
      "name": "hatch_eggs",
      "docs": [
        "Hatch eggs to get miners"
      ],
      "discriminator": [
        131,
        243,
        49,
        50,
        130,
        1,
        42,
        156
      ],
      "accounts": [
        {
          "name": "global_state",
          "writable": true,
          "pda": {
            "seeds": [
              {
                "kind": "const",
                "value": [
                  103,
                  108,
                  111,
                  98,
                  97,
                  108,
                  95,
                  115,
                  116,
                  97,
                  116,
                  101
                ]
              }
            ]
          }
        },
        {
          "name": "user_state",
          "writable": true,
          "pda": {
            "seeds": [
              {
                "kind": "const",
                "value": [
                  117,
                  115,
                  101,
                  114,
                  95,
                  115,
                  116,
                  97,
                  116,
                  101
                ]
              },
              {
                "kind": "account",
                "path": "user"
              }
            ]
          }
        },
        {
          "name": "user",
          "writable": true,
          "signer": true
        },
        {
          "name": "referrer_state",
          "writable": true,
          "optional": true
        }
      ],
      "args": [
        {
          "name": "referrer",
          "type": {
            "option": "pubkey"
          }
        }
      ]
    },
    {
      "name": "init_user",
      "docs": [
        "Initialize user state account"
      ],
      "discriminator": [
        14,
        51,
        68,
        159,
        237,
        78,
        158,
        102
      ],
      "accounts": [
        {
          "name": "user_state",
          "writable": true,
          "pda": {
            "seeds": [
              {
                "kind": "const",
                "value": [
                  117,
                  115,
                  101,
                  114,
                  95,
                  115,
                  116,
                  97,
                  116,
                  101
                ]
              },
              {
                "kind": "account",
                "path": "user"
              }
            ]
          }
        },
        {
          "name": "user",
          "writable": true,
          "signer": true
        },
        {
          "name": "system_program",
          "address": "11111111111111111111111111111111"
        }
      ],
      "args": []
    },
    {
      "name": "initialize",
      "docs": [
        "Initialize the global state (admin only, one-time setup)"
      ],
      "discriminator": [
        175,
        175,
        109,
        31,
        13,
        152,
        155,
        237
      ],
      "accounts": [
        {
          "name": "global_state",
          "writable": true,
          "pda": {
            "seeds": [
              {
                "kind": "const",
                "value": [
                  103,
                  108,
                  111,
                  98,
                  97,
                  108,
                  95,
                  115,
                  116,
                  97,
                  116,
                  101
                ]
              }
            ]
          }
        },
        {
          "name": "authority",
          "writable": true,
          "signer": true
        },
        {
          "name": "vault",
          "writable": true,
          "pda": {
            "seeds": [
              {
                "kind": "const",
                "value": [
                  118,
                  97,
                  117,
                  108,
                  116
                ]
              }
            ]
          }
        },
        {
          "name": "system_program",
          "address": "11111111111111111111111111111111"
        }
      ],
      "args": [
        {
          "name": "seed_amount",
          "type": "u64"
        }
      ]
    },
    {
      "name": "sell_eggs",
      "docs": [
        "Sell eggs for SOL"
      ],
      "discriminator": [
        200,
        209,
        122,
        32,
        249,
        80,
        69,
        88
      ],
      "accounts": [
        {
          "name": "global_state",
          "writable": true,
          "pda": {
            "seeds": [
              {
                "kind": "const",
                "value": [
                  103,
                  108,
                  111,
                  98,
                  97,
                  108,
                  95,
                  115,
                  116,
                  97,
                  116,
                  101
                ]
              }
            ]
          }
        },
        {
          "name": "user_state",
          "writable": true,
          "pda": {
            "seeds": [
              {
                "kind": "const",
                "value": [
                  117,
                  115,
                  101,
                  114,
                  95,
                  115,
                  116,
                  97,
                  116,
                  101
                ]
              },
              {
                "kind": "account",
                "path": "user"
              }
            ]
          }
        },
        {
          "name": "user",
          "writable": true,
          "signer": true
        },
        {
          "name": "vault",
          "writable": true,
          "pda": {
            "seeds": [
              {
                "kind": "const",
                "value": [
                  118,
                  97,
                  117,
                  108,
                  116
                ]
              }
            ]
          }
        },
        {
          "name": "dev_wallet",
          "writable": true
        },
        {
          "name": "system_program",
          "address": "11111111111111111111111111111111"
        }
      ],
      "args": []
    }
  ],
  "accounts": [
    {
      "name": "GlobalState",
      "discriminator": [
        163,
        46,
        74,
        168,
        216,
        123,
        133,
        98
      ]
    },
    {
      "name": "UserState",
      "discriminator": [
        72,
        177,
        85,
        249,
        76,
        167,
        186,
        126
      ]
    }
  ],
  "errors": [
    {
      "code": 6000,
      "name": "NotInitialized",
      "msg": "Contract not initialized"
    },
    {
      "code": 6001,
      "name": "InvalidAmount",
      "msg": "Invalid amount"
    },
    {
      "code": 6002,
      "name": "InvalidSeedAmount",
      "msg": "Invalid seed amount"
    },
    {
      "code": 6003,
      "name": "Overflow",
      "msg": "Overflow occurred"
    },
    {
      "code": 6004,
      "name": "DivisionByZero",
      "msg": "Division by zero"
    },
    {
      "code": 6005,
      "name": "SelfReferral",
      "msg": "Cannot refer yourself"
    },
    {
      "code": 6006,
      "name": "InsufficientFunds",
      "msg": "Insufficient funds in vault"
    }
  ],
  "types": [
    {
      "name": "GlobalState",
      "type": {
        "kind": "struct",
        "fields": [
          {
            "name": "authority",
            "type": "pubkey"
          },
          {
            "name": "dev_wallet",
            "type": "pubkey"
          },
          {
            "name": "market_eggs",
            "type": "u64"
          },
          {
            "name": "initialized",
            "type": "bool"
          },
          {
            "name": "eggs_to_hatch_1miner",
            "type": "u64"
          },
          {
            "name": "dev_fee_val",
            "type": "u8"
          },
          {
            "name": "psn",
            "type": "u64"
          },
          {
            "name": "psnh",
            "type": "u64"
          }
        ]
      }
    },
    {
      "name": "UserState",
      "type": {
        "kind": "struct",
        "fields": [
          {
            "name": "owner",
            "type": "pubkey"
          },
          {
            "name": "hatchery_miners",
            "type": "u64"
          },
          {
            "name": "claimed_eggs",
            "type": "u64"
          },
          {
            "name": "last_hatch",
            "type": "i64"
          },
          {
            "name": "referrer",
            "type": {
              "option": "pubkey"
            }
          }
        ]
      }
    }
  ]
}